hue_mcp_service.py
hue_mcp_service-0.1.0.dist-info/METADATA
hue_mcp_service-0.1.0.dist-info/WHEEL
hue_mcp_service-0.1.0.dist-info/licenses/LICENSE
hue_mcp_service-0.1.0.dist-info/RECORD
