Metadata-Version: 2.4
Name: hue-mcp-service
Version: 0.1.0
Summary: FastMCP service for controlling Philips Hue lights
Project-URL: Homepage, https://github.com/plwp/hue-mcp-service
Project-URL: Repository, https://github.com/plwp/hue-mcp-service
Project-URL: Issues, https://github.com/plwp/hue-mcp-service/issues
Author-email: Claude Code User <user@example.com>
License: Apache-2.0
License-File: LICENSE
Keywords: ai,api,automation,claude,fastmcp,home-automation,hue,iot,lighting,mcp,model-context-protocol,philips-hue,rest-api,smart-home,smart-lights
Classifier: Development Status :: 4 - Beta
Classifier: Environment :: Console
Classifier: Intended Audience :: Developers
Classifier: Intended Audience :: End Users/Desktop
Classifier: License :: OSI Approved :: Apache Software License
Classifier: Natural Language :: English
Classifier: Operating System :: OS Independent
Classifier: Programming Language :: Python :: 3
Classifier: Programming Language :: Python :: 3.8
Classifier: Programming Language :: Python :: 3.9
Classifier: Programming Language :: Python :: 3.10
Classifier: Programming Language :: Python :: 3.11
Classifier: Programming Language :: Python :: 3.12
Classifier: Topic :: Home Automation
Classifier: Topic :: Internet :: WWW/HTTP :: HTTP Servers
Classifier: Topic :: Scientific/Engineering :: Artificial Intelligence
Classifier: Topic :: Software Development :: Libraries :: Python Modules
Classifier: Topic :: System :: Hardware :: Hardware Drivers
Requires-Python: >=3.8
Requires-Dist: fastmcp>=2.0.0
Requires-Dist: qhue>=2.0.0
Requires-Dist: requests>=2.25.0
Provides-Extra: dev
Requires-Dist: black>=22.0.0; extra == 'dev'
Requires-Dist: pytest>=7.0.0; extra == 'dev'
Requires-Dist: ruff>=0.1.0; extra == 'dev'
